datetime_formatter/__datetime.py
datetime_formatter/__datetime_format.py
datetime_formatter/__formats.py
datetime_formatter/__init__.py
datetime_formatter-0.0.2.dist-info/LICENSE
datetime_formatter-0.0.2.dist-info/METADATA
datetime_formatter-0.0.2.dist-info/WHEEL
datetime_formatter-0.0.2.dist-info/top_level.txt
datetime_formatter-0.0.2.dist-info/RECORD
