Metadata-Version: 2.1
Name: datetime-formatter
Version: 0.0.2
Summary: Manipulate and format datetimes
Home-page: https://github.com/nadime/datetime_formatter
Author: nadime
Author-email: scottpriceasher@gmail.com
License: MIT
Platform: any
Classifier: Development Status :: 4 - Beta
Classifier: Intended Audience :: Developers
Classifier: License :: OSI Approved :: MIT License
Classifier: Operating System :: OS Independent
Classifier: Programming Language :: Python
Classifier: Programming Language :: Python :: 3
Classifier: Programming Language :: Python :: 3 :: Only
Classifier: Programming Language :: Python :: Implementation :: CPython
Classifier: Topic :: Software Development :: Libraries :: Python Modules
Classifier: Topic :: Software Development :: Localization
Requires-Python: >=3.8
License-File: LICENSE
Requires-Dist: attr
Requires-Dist: datetime
Requires-Dist: holidays
Requires-Dist: python-dateutil
Requires-Dist: tzlocal
